wrap_glmnet/__init__.py
wrap_glmnet-0.1.0.dist-info/LICENSE
wrap_glmnet-0.1.0.dist-info/METADATA
wrap_glmnet-0.1.0.dist-info/WHEEL
wrap_glmnet-0.1.0.dist-info/top_level.txt
wrap_glmnet-0.1.0.dist-info/RECORD
