Metadata-Version: 2.1
Name: wrap_glmnet
Version: 0.1.0
Summary: Wrap Glmnet
Home-page: https://github.com/maximz/wrap-glmnet
Author: Maxim Zaslavsky
Author-email: maxim@maximz.com
License: MIT license
Classifier: Development Status :: 2 - Pre-Alpha
Classifier: Intended Audience :: Developers
Classifier: License :: OSI Approved :: MIT License
Classifier: Natural Language :: English
Classifier: Programming Language :: Python :: 3
Classifier: Programming Language :: Python :: 3.8
Classifier: Programming Language :: Python :: 3.9
Requires-Python: >=3.8
License-File: LICENSE
Requires-Dist: numpy
Requires-Dist: glmnet >=2.2.1
Requires-Dist: extendanything
Requires-Dist: scikit-learn
Requires-Dist: pandas
Requires-Dist: genetools
Requires-Dist: multiclass-metrics
Requires-Dist: typing-extensions
